{"reporting_entity_name":"Example Entity","reporting_entity_type":"Insurer","plan_name":"Senior Wellness Plan","plan_id_type":"HIOS","plan_id":"SWP004","plan_market_type":"Commercial","last_updated_on":"2024-11-01","version":"1.0","out_of_network":[{"name":"Katie Johnson","billing_code_type":"CPT","billing_code_type_version":"2023","billing_code":"x9458","description":"Example description","allowed_amounts":[{"tin":{"type":"TIN","value":1554602474},"service_code":["x9458"],"billing_class":"Institutional","payments":[{"allowed_amount":3075.94,"billing_code_modifier":[],"providers":[{"billed_charge":9058.83,"npi":[1554602474]}]}]}]}]}