{"reporting_entity_name":"Example Entity","reporting_entity_type":"Insurer","plan_name":"Family Coverage Plan","plan_id_type":"HIOS","plan_id":"FCP003","plan_market_type":"Commercial","last_updated_on":"2024-11-01","version":"1.0","out_of_network":[{"name":"Gregory Young","billing_code_type":"CPT","billing_code_type_version":"2023","billing_code":"l7118","description":"Example description","allowed_amounts":[{"tin":{"type":"TIN","value":3303330439},"service_code":["l7118"],"billing_class":"Institutional","payments":[{"allowed_amount":2339.91,"billing_code_modifier":[],"providers":[{"billed_charge":4694.92,"npi":[3303330439]}]}]}]}]}